benchmarks/__init__.py
benchmarks/benchmark.py
benchmarks/cache.py
benchmarks/datasets.py
benchmarks/faiss_wrappers.py
benchmarks/metrics.py
benchmarks/run_benchmarks.py
m2vdb/__init__.py
m2vdb/cli.py
m2vdb/client.py
m2vdb/collection.py
m2vdb/models.py
m2vdb/server.py
m2vdb/storage.py
m2vdb/indexes/__init__.py
m2vdb/indexes/base.py
m2vdb/indexes/brute_force.py
m2vdb/indexes/ivf.py
m2vdb/indexes/pq.py
m2vdb/indexes/rust_brute_force.py
m2vdb-1.0.0.dist-info/METADATA
m2vdb-1.0.0.dist-info/WHEEL
m2vdb-1.0.0.dist-info/entry_points.txt
m2vdb-1.0.0.dist-info/top_level.txt
m2vdb-1.0.0.dist-info/RECORD
