Metadata-Version: 2.4
Name: m2vdb
Version: 1.0.0
Summary: Educational vector database built from first principles to understand how vector search really works.
Author-email: Milos Milunovic <milunovicmilos@gmail.com>
License: MIT
Project-URL: Homepage, https://github.com/mmilunovic/m2vdb
Project-URL: Repository, https://github.com/mmilunovic/m2vdb
Project-URL: Issues, https://github.com/mmilunovic/m2vdb/issues
Project-URL: Documentation, https://github.com/mmilunovic/m2vdb#readme
Keywords: vector-database,vector-search,embeddings,similarity-search,machine-learning,nearest-neighbors,product-quantization
Classifier: Development Status :: 3 - Alpha
Classifier: Intended Audience :: Developers
Classifier: Intended Audience :: Science/Research
Classifier: Programming Language :: Python :: 3
Classifier: Programming Language :: Python :: 3.12
Classifier: Programming Language :: Rust
Classifier: Topic :: Database
Classifier: Topic :: Scientific/Engineering :: Artificial Intelligence
Classifier: Topic :: Software Development :: Libraries :: Python Modules
Requires-Python: >=3.12
Requires-Dist: cachetools>=6.2.2
Requires-Dist: faiss-cpu>=1.13.0
Requires-Dist: fastapi>=0.121.0
Requires-Dist: httpx>=0.28.1
Requires-Dist: numpy>=2.3.4
Requires-Dist: packaging>=25.0
Requires-Dist: psutil>=7.1.3
Requires-Dist: pydantic>=2.12.3
Requires-Dist: requests>=2.32.3
Requires-Dist: rich>=14.2.0
Requires-Dist: scikit-learn>=1.7.2
Requires-Dist: uvicorn>=0.38.0
Provides-Extra: benchmark
Requires-Dist: faiss-cpu>=1.9.0; extra == "benchmark"
Requires-Dist: rich>=13.9.4; extra == "benchmark"
Requires-Dist: psutil>=6.1.0; extra == "benchmark"
Provides-Extra: all
Requires-Dist: m2vdb[benchmark]; extra == "all"
